z3c/celery/__init__.py
z3c/celery/celery.py
z3c/celery/conftest.py
z3c/celery/ftesting.zcml
z3c/celery/layer.py
z3c/celery/loader.py
z3c/celery/logging.py
z3c/celery/session.py
z3c/celery/testing.py
z3c/celery/tests/__init__.py
z3c/celery/tests/shared_tasks.py
z3c/celery/tests/test_celery.py
z3c/celery/tests/test_layer.py
z3c/celery/tests/test_loader.py
z3c/celery/tests/test_logging.py
z3c/celery/tests/test_session.py
z3c_celery-1.9.0.dist-info/METADATA
z3c_celery-1.9.0.dist-info/WHEEL
z3c_celery-1.9.0.dist-info/licenses/LICENSE.txt
z3c_celery-1.9.0.dist-info/RECORD
